hintbot/__init__.py
hintbot/_version.py
hintbot/application.py
hintbot/handlers.py
hintbot/labextension/package.json
hintbot/labextension/schemas/hintbot/package.json.orig
hintbot/labextension/schemas/hintbot/plugin.json
hintbot/labextension/static/131.437989ae544ccc35a0ae.js
hintbot/labextension/static/396.0feec676ee8dbdf673f3.js
hintbot/labextension/static/747.6c8516cdc5283291d130.js
hintbot/labextension/static/remoteEntry.82630ad58f4c24bbbd85.js
hintbot/labextension/static/style.js
hintbot/labextension/static/third-party-licenses.json
hintbot-4.0.2.data/data/etc/jupyter/jupyter_server_config.d/hintbot.json
hintbot-4.0.2.data/data/share/jupyter/labextensions/hintbot/package.json
hintbot-4.0.2.data/data/share/jupyter/labextensions/hintbot/schemas/hintbot/package.json.orig
hintbot-4.0.2.data/data/share/jupyter/labextensions/hintbot/schemas/hintbot/plugin.json
hintbot-4.0.2.data/data/share/jupyter/labextensions/hintbot/static/131.437989ae544ccc35a0ae.js
hintbot-4.0.2.data/data/share/jupyter/labextensions/hintbot/static/396.0feec676ee8dbdf673f3.js
hintbot-4.0.2.data/data/share/jupyter/labextensions/hintbot/static/747.6c8516cdc5283291d130.js
hintbot-4.0.2.data/data/share/jupyter/labextensions/hintbot/static/remoteEntry.82630ad58f4c24bbbd85.js
hintbot-4.0.2.data/data/share/jupyter/labextensions/hintbot/static/style.js
hintbot-4.0.2.data/data/share/jupyter/labextensions/hintbot/static/third-party-licenses.json
hintbot-4.0.2.data/data/share/jupyter/labextensions/hintbot/install.json
hintbot-4.0.2.dist-info/METADATA
hintbot-4.0.2.dist-info/WHEEL
hintbot-4.0.2.dist-info/licenses/LICENSE
hintbot-4.0.2.dist-info/RECORD
