Metadata-Version: 2.4
Name: hintbot
Version: 4.0.2
Dynamic: Keywords
Summary: A JupyterLab extension.
Project-URL: Homepage, https://github.com/educational-technology-collective/hintbot
Project-URL: Bug Tracker, https://github.com/educational-technology-collective/hintbot/issues
Project-URL: Repository, https://github.com/educational-technology-collective/hintbot.git
Author-email: etc <mengyanw@umich.edu>
License: BSD 3-Clause License
License-File: LICENSE
Classifier: Framework :: Jupyter
Classifier: Framework :: Jupyter :: JupyterLab
Classifier: Framework :: Jupyter :: JupyterLab :: 4
Classifier: Framework :: Jupyter :: JupyterLab :: Extensions
Classifier: Framework :: Jupyter :: JupyterLab :: Extensions :: Prebuilt
Classifier: License :: OSI Approved :: BSD License
Classifier: Programming Language :: Python
Classifier: Programming Language :: Python :: 3
Classifier: Programming Language :: Python :: 3.8
Classifier: Programming Language :: Python :: 3.9
Classifier: Programming Language :: Python :: 3.10
Classifier: Programming Language :: Python :: 3.11
Classifier: Programming Language :: Python :: 3.12
Requires-Python: >=3.8
Requires-Dist: jupyter-server<3,>=2.0.1
Requires-Dist: jupyterlab-pioneer>=1.6.0
